README.txt
setup.cfg
setup.py
collective/__init__.py
collective.transform.multimarkdown.egg-info/PKG-INFO
collective.transform.multimarkdown.egg-info/SOURCES.txt
collective.transform.multimarkdown.egg-info/dependency_links.txt
collective.transform.multimarkdown.egg-info/entry_points.txt
collective.transform.multimarkdown.egg-info/namespace_packages.txt
collective.transform.multimarkdown.egg-info/not-zip-safe
collective.transform.multimarkdown.egg-info/requires.txt
collective.transform.multimarkdown.egg-info/top_level.txt
collective/transform/__init__.py
collective/transform/multimarkdown/__init__.py
collective/transform/multimarkdown/configure.zcml
collective/transform/multimarkdown/multimarkdown_to_html.py
collective/transform/multimarkdown/setuphandlers.py
collective/transform/multimarkdown/profiles/default/collective.transform.multimarkdown-default.txt
collective/transform/multimarkdown/profiles/default/metadata.xml
collective/transform/multimarkdown/profiles/uninstall/collective.transform.multimarkdown-uninstall.txt
collective/transform/multimarkdown/scripts/ASCIIMathML.pm
collective/transform/multimarkdown/scripts/MultiMarkdown.pl
docs/HISTORY.txt
docs/LICENSE.GPL
docs/LICENSE.txt