Metadata-Version: 1.0
Name: collective.transform.multimarkdown
Version: 0.2
Summary: MultiMarkdown text transform for Plone
Home-page: https://www.sixfeetup.com
Author: Jimmy Theis
Author-email: jimmy AT jetheis DOT com
License: GPL
Platform: UNKNOWN
Classifier: Framework :: Plone
Classifier: Programming Language :: Python
Classifier: Topic :: Software Development :: Libraries :: Python Modules
